setup.py
dsndD_prob.egg-info/PKG-INFO
dsndD_prob.egg-info/SOURCES.txt
dsndD_prob.egg-info/dependency_links.txt
dsndD_prob.egg-info/not-zip-safe
dsndD_prob.egg-info/top_level.txt
dsnd_prob/Binomialdistribution.py
dsnd_prob/Gaussiandistribution.py
dsnd_prob/Generaldistribution.py
dsnd_prob/__init__.py