Metadata-Version: 1.0
Name: dsndD-prob
Version: 1.3
Summary: Gaussian distributions
Home-page: UNKNOWN
Author: UNKNOWN
Author-email: UNKNOWN
License: UNKNOWN
Platform: UNKNOWN
